gradio_imagemask/__init__.py
gradio_imagemask/imagemask.py
gradio_imagemask/imagemask.pyi
gradio_imagemask/templates/component/index.js
gradio_imagemask/templates/component/style.css
gradio_imagemask/templates/example/index.js
gradio_imagemask/templates/example/style.css
gradio_imagemask-0.0.1.dist-info/METADATA
gradio_imagemask-0.0.1.dist-info/WHEEL
gradio_imagemask-0.0.1.dist-info/RECORD
